senertec/__init__.py
senertec/board.py
senertec/canipError.py
senertec/canipValue.py
senertec/client.py
senertec/datapoint.py
senertec/energyUnit.py
senertec/lang.py
senertec/obdClass.py
senertec/senertecerror.py
py_senertec-1.0.3.dist-info/LICENSE
py_senertec-1.0.3.dist-info/METADATA
py_senertec-1.0.3.dist-info/WHEEL
py_senertec-1.0.3.dist-info/top_level.txt
py_senertec-1.0.3.dist-info/RECORD
