Metadata-Version: 2.1
Name: py-senertec
Version: 1.0.3
Summary: Senertec energy system gen2 interface.
Home-page: https://github.com/Kleinrotti/py-senertec
Author: Kleinrotti
Author-email: 
Project-URL: Bug Tracker, https://github.com/Kleinrotti/py-senertec/issues
Classifier: Programming Language :: Python :: 3
Classifier: License :: OSI Approved :: MIT License
Classifier: Operating System :: OS Independent
Requires-Python: >=3.10
License-File: LICENSE
Requires-Dist: websocket-client>=1.2.3
Requires-Dist: requests>=2.27
Requires-Dist: beautifulsoup4>=4.11
